__init__.py
ha_conversation_api_forwarder/__init__.py
ha_conversation_api_forwarder/api_forwarder.py
ha_conversation_api_forwarder-0.0.4.dist-info/licenses/LICENSE
ha_conversation_api_forwarder-0.0.4.dist-info/METADATA
ha_conversation_api_forwarder-0.0.4.dist-info/WHEEL
ha_conversation_api_forwarder-0.0.4.dist-info/top_level.txt
ha_conversation_api_forwarder-0.0.4.dist-info/RECORD
